{"attributes":null,"available_perks":null,"filtered_perks":null,"name":null,"category":"Creatures","subcategory":null,"tier":null,"types":null,"territory":null,"rarity":null,"subjects":{"data":[{"id":"4117","type":"creature","attributes":{"id":4117,"name":"Ancient Guardan Taskmaster","level":61,"creature_type":"Elite","slug":"ancient-guardan-taskmaster-69ebe8"}},{"id":"7604","type":"creature","attributes":{"id":7604,"name":"Ancient Guardian Archer","level":14,"creature_type":"Solo","slug":"ancient-guardian-archer-eabb2a"}},{"id":"7605","type":"creature","attributes":{"id":7605,"name":"Ancient Guardian Archer","level":15,"creature_type":"Solo","slug":"ancient-guardian-archer-d90423"}},{"id":"7606","type":"creature","attributes":{"id":7606,"name":"Ancient Guardian Archer","level":16,"creature_type":"Solo","slug":"ancient-guardian-archer-54aeaf"}},{"id":"7607","type":"creature","attributes":{"id":7607,"name":"Ancient Guardian Archer","level":17,"creature_type":"Solo","slug":"ancient-guardian-archer-200b40"}},{"id":"7608","type":"creature","attributes":{"id":7608,"name":"Ancient Guardian Archer","level":18,"creature_type":"Solo","slug":"ancient-guardian-archer-488d37"}},{"id":"7601","type":"creature","attributes":{"id":7601,"name":"Ancient Guardian Archer","level":20,"creature_type":"Solo","slug":"ancient-guardian-archer-eae961"}},{"id":"7609","type":"creature","attributes":{"id":7609,"name":"Ancient Guardian Archer","level":27,"creature_type":"Solo","slug":"ancient-guardian-archer-c4468a"}},{"id":"7610","type":"creature","attributes":{"id":7610,"name":"Ancient Guardian Archer","level":28,"creature_type":"Solo","slug":"ancient-guardian-archer-5f6224"}},{"id":"7611","type":"creature","attributes":{"id":7611,"name":"Ancient Guardian Archer","level":29,"creature_type":"Solo","slug":"ancient-guardian-archer-4c5de7"}},{"id":"7612","type":"creature","attributes":{"id":7612,"name":"Ancient Guardian Archer","level":30,"creature_type":"Solo","slug":"ancient-guardian-archer-7bb15b"}},{"id":"7613","type":"creature","attributes":{"id":7613,"name":"Ancient Guardian Archer","level":31,"creature_type":"Solo","slug":"ancient-guardian-archer-52e11b"}},{"id":"7614","type":"creature","attributes":{"id":7614,"name":"Ancient Guardian Archer","level":32,"creature_type":"Solo","slug":"ancient-guardian-archer-b864d2"}},{"id":"7615","type":"creature","attributes":{"id":7615,"name":"Ancient Guardian Archer","level":33,"creature_type":"Solo","slug":"ancient-guardian-archer-6478b5"}},{"id":"7616","type":"creature","attributes":{"id":7616,"name":"Ancient Guardian Archer","level":34,"creature_type":"Solo","slug":"ancient-guardian-archer-dcc85e"}},{"id":"7617","type":"creature","attributes":{"id":7617,"name":"Ancient Guardian Archer","level":35,"creature_type":"Solo","slug":"ancient-guardian-archer-f73bf1"}},{"id":"7642","type":"creature","attributes":{"id":7642,"name":"Ancient Guardian Archer","level":35,"creature_type":"Solo-","slug":"ancient-guardian-archer-5b4960"}},{"id":"7618","type":"creature","attributes":{"id":7618,"name":"Ancient Guardian Archer","level":36,"creature_type":"Solo","slug":"ancient-guardian-archer-e82ffb"}},{"id":"7619","type":"creature","attributes":{"id":7619,"name":"Ancient Guardian Archer","level":37,"creature_type":"Solo","slug":"ancient-guardian-archer-65c19e"}},{"id":"7620","type":"creature","attributes":{"id":7620,"name":"Ancient Guardian Archer","level":38,"creature_type":"Solo","slug":"ancient-guardian-archer-5ba9de"}},{"id":"7621","type":"creature","attributes":{"id":7621,"name":"Ancient Guardian Archer","level":39,"creature_type":"Solo","slug":"ancient-guardian-archer-7d6f9c"}},{"id":"7622","type":"creature","attributes":{"id":7622,"name":"Ancient Guardian Archer","level":40,"creature_type":"Solo","slug":"ancient-guardian-archer-3a46b2"}},{"id":"7623","type":"creature","attributes":{"id":7623,"name":"Ancient Guardian Archer","level":41,"creature_type":"Solo","slug":"ancient-guardian-archer-2de11f"}},{"id":"7624","type":"creature","attributes":{"id":7624,"name":"Ancient Guardian Archer","level":42,"creature_type":"Solo","slug":"ancient-guardian-archer-656c68"}},{"id":"7625","type":"creature","attributes":{"id":7625,"name":"Ancient Guardian Archer","level":43,"creature_type":"Solo","slug":"ancient-guardian-archer-b853ca"}},{"id":"7626","type":"creature","attributes":{"id":7626,"name":"Ancient Guardian Archer","level":44,"creature_type":"Solo","slug":"ancient-guardian-archer-bee8b1"}},{"id":"7627","type":"creature","attributes":{"id":7627,"name":"Ancient Guardian Archer","level":45,"creature_type":"Solo","slug":"ancient-guardian-archer-08d5fc"}},{"id":"7628","type":"creature","attributes":{"id":7628,"name":"Ancient Guardian Archer","level":46,"creature_type":"Solo","slug":"ancient-guardian-archer-94df3a"}},{"id":"7629","type":"creature","attributes":{"id":7629,"name":"Ancient Guardian Archer","level":47,"creature_type":"Solo","slug":"ancient-guardian-archer-6f4f53"}},{"id":"7630","type":"creature","attributes":{"id":7630,"name":"Ancient Guardian Archer","level":48,"creature_type":"Solo","slug":"ancient-guardian-archer-df56e8"}},{"id":"7631","type":"creature","attributes":{"id":7631,"name":"Ancient Guardian Archer","level":49,"creature_type":"Solo","slug":"ancient-guardian-archer-2af166"}},{"id":"7632","type":"creature","attributes":{"id":7632,"name":"Ancient Guardian Archer","level":50,"creature_type":"Solo","slug":"ancient-guardian-archer-a0ddf7"}},{"id":"7633","type":"creature","attributes":{"id":7633,"name":"Ancient Guardian Archer","level":51,"creature_type":"Solo","slug":"ancient-guardian-archer-6df46a"}},{"id":"7634","type":"creature","attributes":{"id":7634,"name":"Ancient Guardian Archer","level":52,"creature_type":"Solo","slug":"ancient-guardian-archer-5ebcc6"}},{"id":"7635","type":"creature","attributes":{"id":7635,"name":"Ancient Guardian Archer","level":53,"creature_type":"Solo","slug":"ancient-guardian-archer-069045"}},{"id":"7636","type":"creature","attributes":{"id":7636,"name":"Ancient Guardian Archer","level":54,"creature_type":"Solo","slug":"ancient-guardian-archer-9737ef"}},{"id":"7637","type":"creature","attributes":{"id":7637,"name":"Ancient Guardian Archer","level":55,"creature_type":"Solo","slug":"ancient-guardian-archer-85c960"}},{"id":"7638","type":"creature","attributes":{"id":7638,"name":"Ancient Guardian Archer","level":56,"creature_type":"Solo","slug":"ancient-guardian-archer-7590d6"}},{"id":"7639","type":"creature","attributes":{"id":7639,"name":"Ancient Guardian Archer","level":57,"creature_type":"Solo","slug":"ancient-guardian-archer-697f72"}},{"id":"7640","type":"creature","attributes":{"id":7640,"name":"Ancient Guardian Archer","level":58,"creature_type":"Solo","slug":"ancient-guardian-archer-abbd32"}}]},"page":3,"total":5154}